MANIFEST.in
README.md
setup.py
version.py
src/toil_vg/__init__.py
src/toil_vg/context.py
src/toil_vg/iostore.py
src/toil_vg/pedigree_analysis.py
src/toil_vg/singularity.py
src/toil_vg/vg_augment.py
src/toil_vg/vg_call.py
src/toil_vg/vg_calleval.py
src/toil_vg/vg_chunk.py
src/toil_vg/vg_common.py
src/toil_vg/vg_config.py
src/toil_vg/vg_construct.py
src/toil_vg/vg_index.py
src/toil_vg/vg_map.py
src/toil_vg/vg_mapeval.py
src/toil_vg/vg_msga.py
src/toil_vg/vg_pedigree.py
src/toil_vg/vg_plot.py
src/toil_vg/vg_sim.py
src/toil_vg/vg_surject.py
src/toil_vg/vg_toil.py
src/toil_vg/vg_vcfeval.py
src/toil_vg.egg-info/PKG-INFO
src/toil_vg.egg-info/SOURCES.txt
src/toil_vg.egg-info/dependency_links.txt
src/toil_vg.egg-info/entry_points.txt
src/toil_vg.egg-info/requires.txt
src/toil_vg.egg-info/top_level.txt
src/toil_vg/test/__init__.py
src/toil_vg/test/test_vg.py