Metadata-Version: 1.2
Name: toil-vg
Version: 1.6.2a1.dev415
Summary: UC Santa Cruz Computational Genomics Lab's Toil-based VG pipeline
Home-page: https://github.com/BD2KGenomics/toil-vg
Author: UCSC Computational Genomics Lab
Author-email: cgl-toil@googlegroups.com
License: UNKNOWN
Platform: UNKNOWN
Requires-Python: >=3.0
